{"v":"5.12.2","fr":60,"ip":0,"op":80,"w":500,"h":500,"nm":"01. Framer","ddd":0,"assets":[{"id":"comp_0","nm":"02. Animation","fr":60,"layers":[{"ddd":0,"ind":1,"ty":3,"nm":"control","sr":1,"ks":{"o":{"a":0,"k":0,"ix":11},"r":{"a":1,"k":[{"i":{"x":[0.69],"y":[1]},"o":{"x":[0.28],"y":[0]},"t":0,"s":[-12]},{"i":{"x":[0.69],"y":[1]},"o":{"x":[0.28],"y":[0]},"t":20,"s":[12]},{"i":{"x":[0.69],"y":[1]},"o":{"x":[0.28],"y":[0]},"t":40,"s":[-12]},{"i":{"x":[0.69],"y":[1]},"o":{"x":[0.28],"y":[0]},"t":60,"s":[12]},{"t":80,"s":[-12]}],"ix":10},"p":{"a":1,"k":[{"i":{"x":0.69,"y":1},"o":{"x":0.28,"y":0},"t":0,"s":[307.75,281.875,0],"to":[-53.417,29.5,0],"ti":[0,0,0]},{"i":{"x":0.69,"y":1},"o":{"x":0.28,"y":0},"t":20,"s":[194.75,279.625,0],"to":[0,0,0],"ti":[-45.333,19.792,0]},{"i":{"x":0.69,"y":1},"o":{"x":0.28,"y":0},"t":40,"s":[308.25,281.625,0],"to":[1.307,-0.571,0],"ti":[28.75,22.292,0]},{"i":{"x":0.69,"y":1},"o":{"x":0.28,"y":0},"t":60,"s":[195.25,278.375,0],"to":[-1.43,-1.108,0],"ti":[-66.597,21.859,0]},{"t":80,"s":[307.75,281.875,0]}],"ix":2,"l":2},"a":{"a":0,"k":[0,0,0],"ix":1,"l":2},"s":{"a":0,"k":[100,100,100],"ix":6,"l":2}},"ao":0,"ip":0,"op":140,"st":0,"bm":0},{"ddd":0,"ind":2,"ty":4,"nm":"nose","parent":1,"sr":1,"ks":{"o":{"a":0,"k":100,"ix":11},"r":{"a":1,"k":[{"i":{"x":[0.69],"y":[1]},"o":{"x":[0.28],"y":[0]},"t":0,"s":[-0.101]},{"i":{"x":[0.833],"y":[1]},"o":{"x":[0.28],"y":[0]},"t":20,"s":[3.514]},{"i":{"x":[0.69],"y":[1]},"o":{"x":[0.28],"y":[0]},"t":40,"s":[-0.101]},{"i":{"x":[0.833],"y":[1]},"o":{"x":[0.28],"y":[0]},"t":60,"s":[3.514]},{"t":80,"s":[-0.101]}],"ix":10},"p":{"a":1,"k":[{"i":{"x":0.69,"y":1},"o":{"x":0.28,"y":0},"t":0,"s":[14.465,-9.217,0],"to":[0,0,0],"ti":[0,0,0]},{"i":{"x":0.833,"y":1},"o":{"x":0.28,"y":0},"t":20,"s":[-19.352,-17.133,0],"to":[0,0,0],"ti":[0,0,0]},{"i":{"x":0.69,"y":1},"o":{"x":0.28,"y":0},"t":40,"s":[14.465,-9.217,0],"to":[0,0,0],"ti":[0,0,0]},{"i":{"x":0.833,"y":1},"o":{"x":0.28,"y":0},"t":60,"s":[-19.352,-17.133,0],"to":[0,0,0],"ti":[0,0,0]},{"t":80,"s":[14.465,-9.217,0]}],"ix":2,"l":2},"a":{"a":0,"k":[16.917,11.132,0],"ix":1,"l":2},"s":{"a":0,"k":[100,100,100],"ix":6,"l":2}},"ao":0,"shapes":[{"ty":"gr","it":[{"ind":0,"ty":"sh","ix":1,"ks":{"a":0,"k":{"i":[[0,-6.003],[9.205,0],[0,6.003],[-9.204,0]],"o":[[0,6.003],[-9.204,0],[0,-6.003],[9.205,0]],"v":[[16.667,-4.879],[-0.001,10.882],[-16.667,-4.879],[-0.001,-10.857]],"c":true},"ix":2},"nm":"Path 1","mn":"ADBE Vector Shape - Group","hd":false},{"ty":"fl","c":{"a":0,"k":[0.964705942191,0.470588265213,0.709803921569,1],"ix":4},"o":{"a":0,"k":100,"ix":5},"r":1,"bm":0,"nm":"Fill 1","mn":"ADBE Vector Graphic - Fill","hd":false},{"ty":"tr","p":{"a":0,"k":[16.916,11.132],"ix":2},"a":{"a":0,"k":[0,0],"ix":1},"s":{"a":0,"k":[100,100],"ix":3},"r":{"a":0,"k":0,"ix":6},"o":{"a":0,"k":100,"ix":7},"sk":{"a":0,"k":0,"ix":4},"sa":{"a":0,"k":0,"ix":5},"nm":"Transform"}],"nm":"Group 1","np":2,"cix":2,"bm":0,"ix":1,"mn":"ADBE Vector Group","hd":false}],"ip":0,"op":140,"st":0,"ct":1,"bm":0},{"ddd":0,"ind":3,"ty":4,"nm":"eyebrow","parent":1,"sr":1,"ks":{"o":{"a":0,"k":100,"ix":11},"r":{"a":0,"k":0,"ix":10},"p":{"a":0,"k":[0,-72.538,0],"ix":2,"l":2},"a":{"a":0,"k":[51.464,15.422,0],"ix":1,"l":2},"s":{"a":0,"k":[100,100,100],"ix":6,"l":2}},"ao":0,"shapes":[{"ty":"gr","it":[{"ind":0,"ty":"sh","ix":1,"ks":{"a":0,"k":{"i":[[-2.658,-4.292],[-9.607,5.948],[2.657,4.293],[9.607,-5.948]],"o":[[2.658,4.292],[9.607,-5.948],[-2.658,-4.292],[-9.607,5.948]],"v":[[-17.394,10.88],[1.514,6.32],[17.395,-10.66],[-8.11,-9.224]],"c":true},"ix":2},"nm":"Path 1","mn":"ADBE Vector Shape - Group","hd":false},{"ty":"fl","c":{"a":0,"k":[0.427451010311,0,0.176470588235,1],"ix":4},"o":{"a":0,"k":100,"ix":5},"r":1,"bm":0,"nm":"Fill 1","mn":"ADBE Vector Graphic - Fill","hd":false},{"ty":"tr","p":{"a":1,"k":[{"i":{"x":0.72,"y":1},"o":{"x":0.33,"y":0},"t":0,"s":[100.129,19.654],"to":[0,0],"ti":[0,0]},{"i":{"x":0.833,"y":1},"o":{"x":0.33,"y":0},"t":20,"s":[73.142,4.48],"to":[0,0],"ti":[0,0]},{"i":{"x":0.72,"y":1},"o":{"x":0.33,"y":0},"t":40,"s":[100.129,19.654],"to":[0,0],"ti":[0,0]},{"i":{"x":0.833,"y":1},"o":{"x":0.33,"y":0},"t":60,"s":[73.142,4.48],"to":[0,0],"ti":[0,0]},{"t":80,"s":[100.129,19.654]}],"ix":2},"a":{"a":0,"k":[0,0],"ix":1},"s":{"a":1,"k":[{"i":{"x":[0.72,0.72],"y":[1,1]},"o":{"x":[0.33,0.33],"y":[0,0]},"t":0,"s":[84.947,84.947]},{"i":{"x":[0.833,0.833],"y":[1,1]},"o":{"x":[0.33,0.33],"y":[0,0]},"t":20,"s":[127.219,127.219]},{"i":{"x":[0.72,0.72],"y":[1,1]},"o":{"x":[0.33,0.33],"y":[0,0]},"t":40,"s":[84.947,84.947]},{"i":{"x":[0.833,0.833],"y":[1,1]},"o":{"x":[0.33,0.33],"y":[0,0]},"t":60,"s":[127.219,127.219]},{"t":80,"s":[84.947,84.947]}],"ix":3},"r":{"a":0,"k":0,"ix":6},"o":{"a":0,"k":100,"ix":7},"sk":{"a":0,"k":0,"ix":4},"sa":{"a":0,"k":0,"ix":5},"nm":"Transform"}],"nm":"Group 1","np":2,"cix":2,"bm":0,"ix":1,"mn":"ADBE Vector Group","hd":false},{"ty":"gr","it":[{"ind":0,"ty":"sh","ix":1,"ks":{"a":0,"k":{"i":[[2.658,-4.292],[9.607,5.948],[-2.657,4.293],[-9.607,-5.948]],"o":[[-2.658,4.292],[-9.607,-5.948],[2.658,-4.292],[9.607,5.948]],"v":[[17.395,10.88],[-1.514,6.32],[-17.396,-10.66],[8.111,-9.224]],"c":true},"ix":2},"nm":"Path 1","mn":"ADBE Vector Shape - Group","hd":false},{"ty":"fl","c":{"a":0,"k":[0.427451010311,0,0.176470588235,1],"ix":4},"o":{"a":0,"k":100,"ix":5},"r":1,"bm":0,"nm":"Fill 1","mn":"ADBE Vector Graphic - Fill","hd":false},{"ty":"tr","p":{"a":1,"k":[{"i":{"x":0.72,"y":1},"o":{"x":0.33,"y":0},"t":0,"s":[27.211,11.779],"to":[0,0],"ti":[0,0]},{"i":{"x":0.833,"y":1},"o":{"x":0.33,"y":0},"t":20,"s":[0.843,11.597],"to":[0,0],"ti":[0,0]},{"i":{"x":0.72,"y":1},"o":{"x":0.33,"y":0},"t":40,"s":[27.211,11.779],"to":[0,0],"ti":[0,0]},{"i":{"x":0.833,"y":1},"o":{"x":0.33,"y":0},"t":60,"s":[0.843,11.597],"to":[0,0],"ti":[0,0]},{"t":80,"s":[27.211,11.779]}],"ix":2},"a":{"a":0,"k":[0,0],"ix":1},"s":{"a":1,"k":[{"i":{"x":[0.72,0.72],"y":[1,1]},"o":{"x":[0.33,0.33],"y":[0,0]},"t":0,"s":[121.979,121.979]},{"i":{"x":[0.833,0.833],"y":[1,1]},"o":{"x":[0.33,0.33],"y":[0,0]},"t":20,"s":[76.008,76.008]},{"i":{"x":[0.72,0.72],"y":[1,1]},"o":{"x":[0.33,0.33],"y":[0,0]},"t":40,"s":[121.979,121.979]},{"i":{"x":[0.833,0.833],"y":[1,1]},"o":{"x":[0.33,0.33],"y":[0,0]},"t":60,"s":[76.008,76.008]},{"t":80,"s":[121.979,121.979]}],"ix":3},"r":{"a":0,"k":0,"ix":6},"o":{"a":0,"k":100,"ix":7},"sk":{"a":0,"k":0,"ix":4},"sa":{"a":0,"k":0,"ix":5},"nm":"Transform"}],"nm":"Group 2","np":2,"cix":2,"bm":0,"ix":2,"mn":"ADBE Vector Group","hd":false}],"ip":0,"op":140,"st":0,"ct":1,"bm":0},{"ddd":0,"ind":4,"ty":4,"nm":"eyes","parent":1,"sr":1,"ks":{"o":{"a":0,"k":100,"ix":11},"r":{"a":0,"k":0,"ix":10},"p":{"a":0,"k":[-0.778,-45.45,0],"ix":2,"l":2},"a":{"a":0,"k":[120.111,47.772,0],"ix":1,"l":2},"s":{"a":0,"k":[100,100,100],"ix":6,"l":2}},"ao":0,"shapes":[{"ty":"gr","it":[{"ind":0,"ty":"sh","ix":1,"ks":{"a":1,"k":[{"i":{"x":0.69,"y":1},"o":{"x":0.28,"y":0},"t":0,"s":[{"i":[[0,0],[22.875,-36.862],[-19.833,1.306]],"o":[[0,0],[11.05,-7.683],[0,0]],"v":[[21.097,-8.95],[-21,25.328],[17.031,9.168]],"c":false}]},{"i":{"x":0.69,"y":1},"o":{"x":0.28,"y":0},"t":20,"s":[{"i":[[0,0],[27.378,-37.587],[-24.667,-4.391]],"o":[[0,0],[12.346,-7.3],[0,0]],"v":[[30.413,-25.243],[-52.136,17.123],[14.805,3.507]],"c":false}]},{"i":{"x":0.69,"y":1},"o":{"x":0.28,"y":0},"t":40,"s":[{"i":[[0,0],[22.875,-36.862],[-19.833,1.306]],"o":[[0,0],[11.05,-7.683],[0,0]],"v":[[21.097,-8.95],[-21,25.328],[17.031,9.168]],"c":false}]},{"i":{"x":0.69,"y":1},"o":{"x":0.28,"y":0},"t":60,"s":[{"i":[[0,0],[27.378,-37.587],[-24.667,-4.391]],"o":[[0,0],[12.346,-7.3],[0,0]],"v":[[30.413,-25.243],[-52.136,17.123],[14.805,3.507]],"c":false}]},{"t":80,"s":[{"i":[[0,0],[22.875,-36.862],[-19.833,1.306]],"o":[[0,0],[11.05,-7.683],[0,0]],"v":[[21.097,-8.95],[-21,25.328],[17.031,9.168]],"c":false}]}],"ix":2},"nm":"Path 1","mn":"ADBE Vector Shape - Group","hd":false},{"ty":"st","c":{"a":0,"k":[0.309803921569,0.125490196078,0.090196078431,1],"ix":3},"o":{"a":0,"k":100,"ix":4},"w":{"a":0,"k":10,"ix":5},"lc":2,"lj":2,"bm":0,"nm":"Stroke 1","mn":"ADBE Vector Graphic - Stroke","hd":false},{"ty":"tr","p":{"a":0,"k":[177.386,47.772],"ix":2},"a":{"a":0,"k":[0,0],"ix":1},"s":{"a":0,"k":[100,100],"ix":3},"r":{"a":0,"k":0,"ix":6},"o":{"a":0,"k":100,"ix":7},"sk":{"a":0,"k":0,"ix":4},"sa":{"a":0,"k":0,"ix":5},"nm":"Transform"}],"nm":"Group 1","np":2,"cix":2,"bm":0,"ix":1,"mn":"ADBE Vector Group","hd":false},{"ty":"gr","it":[{"ind":0,"ty":"sh","ix":1,"ks":{"a":1,"k":[{"i":{"x":0.69,"y":1},"o":{"x":0.28,"y":0},"t":0,"s":[{"i":[[0,0],[-26.149,-43.664],[31.111,-0.888]],"o":[[0,0],[-20.339,-13.099],[0,0]],"v":[[-38.614,-22.327],[38.614,22.327],[-24.392,2.117]],"c":false}]},{"i":{"x":0.69,"y":1},"o":{"x":0.28,"y":0},"t":20,"s":[{"i":[[0,0],[-21.83,-35.106],[5.935,-1.526]],"o":[[0,0],[-16.397,-15.558],[0,0]],"v":[[-30.416,-17.425],[15.963,14.363],[-19.293,2.055]],"c":false}]},{"i":{"x":0.69,"y":1},"o":{"x":0.28,"y":0},"t":40,"s":[{"i":[[0,0],[-26.149,-43.664],[31.111,-0.888]],"o":[[0,0],[-20.339,-13.099],[0,0]],"v":[[-38.614,-22.327],[38.614,22.327],[-24.392,2.117]],"c":false}]},{"i":{"x":0.69,"y":1},"o":{"x":0.28,"y":0},"t":60,"s":[{"i":[[0,0],[-21.83,-35.106],[5.935,-1.526]],"o":[[0,0],[-16.397,-15.558],[0,0]],"v":[[-30.416,-17.425],[15.963,14.363],[-19.293,2.055]],"c":false}]},{"t":80,"s":[{"i":[[0,0],[-26.149,-43.664],[31.111,-0.888]],"o":[[0,0],[-20.339,-13.099],[0,0]],"v":[[-38.614,-22.327],[38.614,22.327],[-24.392,2.117]],"c":false}]}],"ix":2},"nm":"Path 1","mn":"ADBE Vector Shape - Group","hd":false},{"ty":"st","c":{"a":0,"k":[0.309803921569,0.125490196078,0.090196078431,1],"ix":3},"o":{"a":0,"k":100,"ix":4},"w":{"a":0,"k":10,"ix":5},"lc":2,"lj":2,"bm":0,"nm":"Stroke 1","mn":"ADBE Vector Graphic - Stroke","hd":false},{"ty":"tr","p":{"a":0,"k":[63.614,47.772],"ix":2},"a":{"a":0,"k":[0,0],"ix":1},"s":{"a":0,"k":[100,100],"ix":3},"r":{"a":0,"k":0,"ix":6},"o":{"a":0,"k":100,"ix":7},"sk":{"a":0,"k":0,"ix":4},"sa":{"a":0,"k":0,"ix":5},"nm":"Transform"}],"nm":"Group 2","np":2,"cix":2,"bm":0,"ix":2,"mn":"ADBE Vector Group","hd":false}],"ip":0,"op":140,"st":0,"ct":1,"bm":0},{"ddd":0,"ind":5,"ty":4,"nm":"mouth","parent":1,"sr":1,"ks":{"o":{"a":0,"k":100,"ix":11},"r":{"a":0,"k":0,"ix":10},"p":{"a":0,"k":[0,25.84,0],"ix":2,"l":2},"a":{"a":0,"k":[64.625,49.938,0],"ix":1,"l":2},"s":{"a":0,"k":[100,100,100],"ix":6,"l":2}},"ao":0,"shapes":[{"ty":"gr","it":[{"ind":0,"ty":"sh","ix":1,"ks":{"a":1,"k":[{"i":{"x":0.69,"y":1},"o":{"x":0.28,"y":0},"t":0,"s":[{"i":[[0,0],[-4.189,60.359]],"o":[[9.236,53.453],[0,0]],"v":[[-33.138,-30.573],[38.034,-24.182]],"c":false}]},{"i":{"x":0.69,"y":1},"o":{"x":0.28,"y":0},"t":20,"s":[{"i":[[0,0],[-8.713,53.322]],"o":[[2.993,56.507],[0,0]],"v":[[-39.318,-30.793],[26.278,-31.395]],"c":false}]},{"i":{"x":0.69,"y":1},"o":{"x":0.28,"y":0},"t":40,"s":[{"i":[[0,0],[-4.189,60.359]],"o":[[9.236,53.453],[0,0]],"v":[[-33.138,-30.573],[38.034,-24.182]],"c":false}]},{"i":{"x":0.69,"y":1},"o":{"x":0.28,"y":0},"t":60,"s":[{"i":[[0,0],[-8.713,53.322]],"o":[[2.993,56.507],[0,0]],"v":[[-39.318,-30.793],[26.278,-31.395]],"c":false}]},{"t":80,"s":[{"i":[[0,0],[-4.189,60.359]],"o":[[9.236,53.453],[0,0]],"v":[[-33.138,-30.573],[38.034,-24.182]],"c":false}]}],"ix":2},"nm":"Path 1","mn":"ADBE Vector Shape - Group","hd":false},{"ty":"st","c":{"a":0,"k":[0.309803921569,0.125490196078,0.090196078431,1],"ix":3},"o":{"a":0,"k":100,"ix":4},"w":{"a":0,"k":8,"ix":5},"lc":2,"lj":2,"bm":0,"nm":"Stroke 1","mn":"ADBE Vector Graphic - Stroke","hd":false},{"ty":"tr","p":{"a":0,"k":[64.625,49.938],"ix":2},"a":{"a":0,"k":[0,0],"ix":1},"s":{"a":0,"k":[100,100],"ix":3},"r":{"a":0,"k":0,"ix":6},"o":{"a":0,"k":100,"ix":7},"sk":{"a":0,"k":0,"ix":4},"sa":{"a":0,"k":0,"ix":5},"nm":"Transform"}],"nm":"Group 1","np":2,"cix":2,"bm":0,"ix":1,"mn":"ADBE Vector Group","hd":false},{"ty":"gr","it":[{"ind":0,"ty":"sh","ix":1,"ks":{"a":1,"k":[{"i":{"x":0.69,"y":1},"o":{"x":0.28,"y":0},"t":0,"s":[{"i":[[0,0],[0,0]],"o":[[0,0],[0,0]],"v":[[77.545,25.145],[71.139,64.048]],"c":false}]},{"i":{"x":0.69,"y":1},"o":{"x":0.28,"y":0},"t":20,"s":[{"i":[[0,0],[0,0]],"o":[[0,0],[0,0]],"v":[[45.571,16.606],[47.687,54.72]],"c":false}]},{"i":{"x":0.69,"y":1},"o":{"x":0.28,"y":0},"t":40,"s":[{"i":[[0,0],[0,0]],"o":[[0,0],[0,0]],"v":[[77.545,25.145],[71.139,64.048]],"c":false}]},{"i":{"x":0.69,"y":1},"o":{"x":0.28,"y":0},"t":60,"s":[{"i":[[0,0],[0,0]],"o":[[0,0],[0,0]],"v":[[45.571,16.606],[47.687,54.72]],"c":false}]},{"t":80,"s":[{"i":[[0,0],[0,0]],"o":[[0,0],[0,0]],"v":[[77.545,25.145],[71.139,64.048]],"c":false}]}],"ix":2},"nm":"Path 1","mn":"ADBE Vector Shape - Group","hd":false},{"ty":"st","c":{"a":0,"k":[0.725490196078,0.501960784314,0.388235324037,1],"ix":3},"o":{"a":0,"k":100,"ix":4},"w":{"a":0,"k":4,"ix":5},"lc":2,"lj":2,"bm":0,"nm":"Stroke 1","mn":"ADBE Vector Graphic - Stroke","hd":false},{"ty":"tr","p":{"a":0,"k":[0,0],"ix":2},"a":{"a":0,"k":[0,0],"ix":1},"s":{"a":0,"k":[100,100],"ix":3},"r":{"a":0,"k":0,"ix":6},"o":{"a":0,"k":100,"ix":7},"sk":{"a":0,"k":0,"ix":4},"sa":{"a":0,"k":0,"ix":5},"nm":"Transform"}],"nm":"Group 2","np":2,"cix":2,"bm":0,"ix":2,"mn":"ADBE Vector Group","hd":false}],"ip":0,"op":140,"st":0,"ct":1,"bm":0},{"ddd":0,"ind":6,"ty":4,"nm":"tongue","parent":1,"sr":1,"ks":{"o":{"a":0,"k":100,"ix":11},"r":{"a":0,"k":0,"ix":10},"p":{"a":0,"k":[-0.092,115.334,0],"ix":2,"l":2},"a":{"a":0,"k":[94.226,102.334,0],"ix":1,"l":2},"s":{"a":0,"k":[100,100,100],"ix":6,"l":2}},"ao":0,"shapes":[{"ty":"gr","it":[{"ind":0,"ty":"sh","ix":1,"ks":{"a":1,"k":[{"i":{"x":0.833,"y":0.833},"o":{"x":0.167,"y":0.167},"t":0,"s":[{"i":[[0,0],[-32,-27.843]],"o":[[0,0],[22.237,19.348]],"v":[[103.141,30.281],[144.396,87.31]],"c":false}]},{"i":{"x":0.833,"y":0.833},"o":{"x":0.167,"y":0.167},"t":10,"s":[{"i":[[0,0],[-37.251,-40.132]],"o":[[0,0],[20.052,21.603]],"v":[[95.807,26.841],[130.271,102.964]],"c":false}]},{"i":{"x":0.833,"y":0.833},"o":{"x":0.167,"y":0.167},"t":20,"s":[{"i":[[0,0],[26.035,-20.28]],"o":[[0,0],[-23.253,18.113]],"v":[[76.841,24.452],[46.775,72.066]],"c":false}]},{"i":{"x":0.833,"y":0.833},"o":{"x":0.167,"y":0.167},"t":30,"s":[{"i":[[0,0],[29.968,-17.679]],"o":[[0,0],[-25.387,14.977]],"v":[[90.002,28.536],[56.466,81.427]],"c":false}]},{"i":{"x":0.833,"y":0.833},"o":{"x":0.167,"y":0.167},"t":40,"s":[{"i":[[0,0],[-32,-27.843]],"o":[[0,0],[22.237,19.348]],"v":[[103.141,30.281],[144.396,87.31]],"c":false}]},{"i":{"x":0.833,"y":0.833},"o":{"x":0.167,"y":0.167},"t":50,"s":[{"i":[[0,0],[-37.251,-40.132]],"o":[[0,0],[20.052,21.603]],"v":[[95.807,26.841],[130.271,102.964]],"c":false}]},{"i":{"x":0.833,"y":0.833},"o":{"x":0.167,"y":0.167},"t":60,"s":[{"i":[[0,0],[26.035,-20.28]],"o":[[0,0],[-23.253,18.113]],"v":[[76.841,24.452],[46.775,72.066]],"c":false}]},{"i":{"x":0.833,"y":0.833},"o":{"x":0.167,"y":0.167},"t":70,"s":[{"i":[[0,0],[29.968,-17.679]],"o":[[0,0],[-25.387,14.977]],"v":[[90.002,28.536],[56.466,81.427]],"c":false}]},{"t":80,"s":[{"i":[[0,0],[-32,-27.843]],"o":[[0,0],[22.237,19.348]],"v":[[103.141,30.281],[144.396,87.31]],"c":false}]}],"ix":2},"nm":"Path 1","mn":"ADBE Vector Shape - Group","hd":false},{"ty":"st","c":{"a":0,"k":[0.89019613827,0,0.356862745098,1],"ix":3},"o":{"a":0,"k":100,"ix":4},"w":{"a":0,"k":6,"ix":5},"lc":2,"lj":2,"bm":0,"nm":"Stroke 1","mn":"ADBE Vector Graphic - Stroke","hd":false},{"ty":"tr","p":{"a":0,"k":[0,0],"ix":2},"a":{"a":0,"k":[0,0],"ix":1},"s":{"a":0,"k":[100,100],"ix":3},"r":{"a":0,"k":0,"ix":6},"o":{"a":0,"k":100,"ix":7},"sk":{"a":0,"k":0,"ix":4},"sa":{"a":0,"k":0,"ix":5},"nm":"Transform"}],"nm":"Shape 1","np":3,"cix":2,"bm":0,"ix":1,"mn":"ADBE Vector Group","hd":false},{"ty":"gr","it":[{"ind":0,"ty":"sh","ix":1,"ks":{"a":1,"k":[{"i":{"x":0.833,"y":0.833},"o":{"x":0.167,"y":0.167},"t":0,"s":[{"i":[[0,0],[10.977,30.422],[-26.065,-51.703],[-30.466,13.077],[34.723,22.321]],"o":[[-9.201,23.664],[0,0],[27.576,54.701],[40.729,-17.483],[-54.883,-35.28]],"v":[[32.949,-91.029],[-27.044,-96.191],[-2.851,1.459],[104.163,54.203],[84.678,-26.801]],"c":true}]},{"i":{"x":0.833,"y":0.833},"o":{"x":0.167,"y":0.167},"t":10,"s":[{"i":[[0,0],[12.125,24.781],[-18.851,-49.232],[-29.45,12.923],[37.381,25.056]],"o":[[-10.098,22.366],[0,0],[22.826,59.613],[52.749,-23.147],[-67.988,-45.571]],"v":[[26.664,-96.237],[-27.524,-93.188],[-21.303,9.87],[78.098,75.245],[73.695,-22.807]],"c":true}]},{"i":{"x":0.833,"y":0.833},"o":{"x":0.167,"y":0.167},"t":20,"s":[{"i":[[0,0],[12.685,24.695],[35.845,-21.94],[-44.248,-23.176],[-17.899,57.701]],"o":[[-14.632,24.563],[0,0],[-33.64,20.59],[34.306,17.969],[16.166,-52.115]],"v":[[18.925,-98.49],[-32.809,-94.455],[-71.747,-36.956],[-94.405,53.673],[10.767,-1.407]],"c":true}]},{"i":{"x":0.833,"y":0.833},"o":{"x":0.167,"y":0.167},"t":30,"s":[{"i":[[0,0],[11.377,26.042],[38.66,-14.652],[-28.777,-20.102],[-23.621,52.968]],"o":[[-12.816,17.597],[0,0],[-72.34,27.416],[34.213,23.899],[22.135,-49.636]],"v":[[25.011,-92.584],[-26.337,-91.162],[-62.693,-31.385],[-99.58,64.679],[16.641,10.42]],"c":true}]},{"i":{"x":0.833,"y":0.833},"o":{"x":0.167,"y":0.167},"t":40,"s":[{"i":[[0,0],[10.977,30.422],[-26.065,-51.703],[-30.466,13.077],[34.723,22.321]],"o":[[-9.201,23.664],[0,0],[27.576,54.701],[40.729,-17.483],[-54.883,-35.28]],"v":[[32.949,-91.029],[-27.044,-96.191],[-2.851,1.459],[104.163,54.203],[84.678,-26.801]],"c":true}]},{"i":{"x":0.833,"y":0.833},"o":{"x":0.167,"y":0.167},"t":50,"s":[{"i":[[0,0],[12.125,24.781],[-18.851,-49.232],[-29.45,12.923],[37.381,25.056]],"o":[[-10.098,22.366],[0,0],[22.826,59.613],[52.749,-23.147],[-67.988,-45.571]],"v":[[26.664,-96.237],[-27.524,-93.188],[-21.303,9.87],[78.098,75.245],[73.695,-22.807]],"c":true}]},{"i":{"x":0.833,"y":0.833},"o":{"x":0.167,"y":0.167},"t":60,"s":[{"i":[[0,0],[12.685,24.695],[35.845,-21.94],[-44.248,-23.176],[-17.899,57.701]],"o":[[-14.632,24.563],[0,0],[-33.64,20.59],[34.306,17.969],[16.166,-52.115]],"v":[[18.925,-98.49],[-32.809,-94.455],[-71.747,-36.956],[-94.405,53.673],[10.767,-1.407]],"c":true}]},{"i":{"x":0.833,"y":0.833},"o":{"x":0.167,"y":0.167},"t":70,"s":[{"i":[[0,0],[11.377,26.042],[38.66,-14.652],[-28.777,-20.102],[-23.621,52.968]],"o":[[-12.816,17.597],[0,0],[-72.34,27.416],[34.213,23.899],[22.135,-49.636]],"v":[[25.011,-92.584],[-26.337,-91.162],[-62.693,-31.385],[-99.58,64.679],[16.641,10.42]],"c":true}]},{"t":80,"s":[{"i":[[0,0],[10.977,30.422],[-26.065,-51.703],[-30.466,13.077],[34.723,22.321]],"o":[[-9.201,23.664],[0,0],[27.576,54.701],[40.729,-17.483],[-54.883,-35.28]],"v":[[32.949,-91.029],[-27.044,-96.191],[-2.851,1.459],[104.163,54.203],[84.678,-26.801]],"c":true}]}],"ix":2},"nm":"Path 1","mn":"ADBE Vector Shape - Group","hd":false},{"ty":"st","c":{"a":0,"k":[0.89019613827,0,0.356862745098,1],"ix":3},"o":{"a":0,"k":100,"ix":4},"w":{"a":0,"k":6,"ix":5},"lc":2,"lj":2,"bm":0,"nm":"Stroke 1","mn":"ADBE Vector Graphic - Stroke","hd":false},{"ty":"fl","c":{"a":0,"k":[1,0.439215716194,0.549019607843,1],"ix":4},"o":{"a":0,"k":100,"ix":5},"r":1,"bm":0,"nm":"Fill 1","mn":"ADBE Vector Graphic - Fill","hd":false},{"ty":"tr","p":{"a":0,"k":[94.226,102.334],"ix":2},"a":{"a":0,"k":[0,0],"ix":1},"s":{"a":0,"k":[100,100],"ix":3},"r":{"a":0,"k":0,"ix":6},"o":{"a":0,"k":100,"ix":7},"sk":{"a":0,"k":0,"ix":4},"sa":{"a":0,"k":0,"ix":5},"nm":"Transform"}],"nm":"Group 2","np":3,"cix":2,"bm":0,"ix":2,"mn":"ADBE Vector Group","hd":false}],"ip":0,"op":140,"st":0,"ct":1,"bm":0},{"ddd":0,"ind":7,"ty":4,"nm":"mustache","sr":1,"ks":{"o":{"a":0,"k":100,"ix":11},"r":{"a":0,"k":0,"ix":10},"p":{"a":0,"k":[252.5,348.081,0],"ix":2,"l":2},"a":{"a":0,"k":[179.188,34.173,0],"ix":1,"l":2},"s":{"a":0,"k":[100,100,100],"ix":6,"l":2}},"ao":0,"shapes":[{"ty":"gr","it":[{"ind":0,"ty":"sh","ix":1,"ks":{"a":1,"k":[{"i":{"x":0.65,"y":1},"o":{"x":0.34,"y":0},"t":0,"s":[{"i":[[0,0],[4.651,-4.119]],"o":[[-7.57,-1.58],[0,0]],"v":[[20.97,-90.52],[2.749,-86.73]],"c":false}]},{"i":{"x":0.65,"y":1},"o":{"x":0.34,"y":0},"t":20,"s":[{"i":[[0,0],[8.651,2.881]],"o":[[-6.57,-9.33],[0,0]],"v":[[13.97,-5.52],[-9.751,-21.73]],"c":false}]},{"i":{"x":0.65,"y":1},"o":{"x":0.34,"y":0},"t":40,"s":[{"i":[[0,0],[4.651,-4.119]],"o":[[-7.57,-1.58],[0,0]],"v":[[20.97,-90.52],[2.749,-86.73]],"c":false}]},{"i":{"x":0.65,"y":1},"o":{"x":0.34,"y":0},"t":60,"s":[{"i":[[0,0],[8.651,2.881]],"o":[[-6.57,-9.33],[0,0]],"v":[[13.97,-5.52],[-9.751,-21.73]],"c":false}]},{"t":80,"s":[{"i":[[0,0],[4.651,-4.119]],"o":[[-7.57,-1.58],[0,0]],"v":[[20.97,-90.52],[2.749,-86.73]],"c":false}]}],"ix":2},"nm":"Path 1","mn":"ADBE Vector Shape - Group","hd":false},{"ty":"st","c":{"a":0,"k":[0.317647058824,0.149019607843,0.094117654539,1],"ix":3},"o":{"a":0,"k":100,"ix":4},"w":{"a":0,"k":6,"ix":5},"lc":2,"lj":2,"bm":0,"nm":"Stroke 1","mn":"ADBE Vector Graphic - Stroke","hd":false},{"ty":"tr","p":{"a":0,"k":[325.788,34.941],"ix":2},"a":{"a":0,"k":[0,0],"ix":1},"s":{"a":0,"k":[100,100],"ix":3},"r":{"a":0,"k":0,"ix":6},"o":{"a":0,"k":100,"ix":7},"sk":{"a":0,"k":0,"ix":4},"sa":{"a":0,"k":0,"ix":5},"nm":"Transform"}],"nm":"Group 1","np":2,"cix":2,"bm":0,"ix":1,"mn":"ADBE Vector Group","hd":false},{"ty":"gr","it":[{"ind":0,"ty":"sh","ix":1,"ks":{"a":1,"k":[{"i":{"x":0.65,"y":1},"o":{"x":0.34,"y":0},"t":0,"s":[{"i":[[0,0],[5.738,-2.908]],"o":[[-10.188,-3.231],[0,0]],"v":[[17.338,-92.089],[-8.088,-88.411]],"c":false}]},{"i":{"x":0.65,"y":1},"o":{"x":0.34,"y":0},"t":20,"s":[{"i":[[0,0],[8.488,1.092]],"o":[[-10.938,-12.731],[0,0]],"v":[[13.338,-7.089],[-17.588,-23.911]],"c":false}]},{"i":{"x":0.65,"y":1},"o":{"x":0.34,"y":0},"t":40,"s":[{"i":[[0,0],[5.738,-2.908]],"o":[[-10.188,-3.231],[0,0]],"v":[[17.338,-92.089],[-8.088,-88.411]],"c":false}]},{"i":{"x":0.65,"y":1},"o":{"x":0.34,"y":0},"t":60,"s":[{"i":[[0,0],[8.488,1.092]],"o":[[-10.938,-12.731],[0,0]],"v":[[13.338,-7.089],[-17.588,-23.911]],"c":false}]},{"t":80,"s":[{"i":[[0,0],[5.738,-2.908]],"o":[[-10.188,-3.231],[0,0]],"v":[[17.338,-92.089],[-8.088,-88.411]],"c":false}]}],"ix":2},"nm":"Path 1","mn":"ADBE Vector Shape - Group","hd":false},{"ty":"st","c":{"a":0,"k":[0.317647058824,0.149019607843,0.094117654539,1],"ix":3},"o":{"a":0,"k":100,"ix":4},"w":{"a":0,"k":6,"ix":5},"lc":2,"lj":2,"bm":0,"nm":"Stroke 1","mn":"ADBE Vector Graphic - Stroke","hd":false},{"ty":"tr","p":{"a":0,"k":[335.288,24.911],"ix":2},"a":{"a":0,"k":[0,0],"ix":1},"s":{"a":0,"k":[100,100],"ix":3},"r":{"a":0,"k":0,"ix":6},"o":{"a":0,"k":100,"ix":7},"sk":{"a":0,"k":0,"ix":4},"sa":{"a":0,"k":0,"ix":5},"nm":"Transform"}],"nm":"Group 2","np":2,"cix":2,"bm":0,"ix":2,"mn":"ADBE Vector Group","hd":false},{"ty":"gr","it":[{"ind":0,"ty":"sh","ix":1,"ks":{"a":1,"k":[{"i":{"x":0.65,"y":1},"o":{"x":0.34,"y":0},"t":0,"s":[{"i":[[0,0],[-9.354,1.436]],"o":[[3.892,-8.254],[0,0]],"v":[[-15.772,-3.905],[3.973,-19.095]],"c":false}]},{"i":{"x":0.65,"y":1},"o":{"x":0.34,"y":0},"t":20,"s":[{"i":[[0,0],[-7.104,-4.814]],"o":[[6.142,-1.254],[0,0]],"v":[[-36.772,-114.655],[-12.527,-110.845]],"c":false}]},{"i":{"x":0.65,"y":1},"o":{"x":0.34,"y":0},"t":40,"s":[{"i":[[0,0],[-9.354,1.436]],"o":[[3.892,-8.254],[0,0]],"v":[[-15.772,-3.905],[3.973,-19.095]],"c":false}]},{"i":{"x":0.65,"y":1},"o":{"x":0.34,"y":0},"t":60,"s":[{"i":[[0,0],[-7.104,-4.814]],"o":[[6.142,-1.254],[0,0]],"v":[[-36.772,-114.655],[-12.527,-110.845]],"c":false}]},{"t":80,"s":[{"i":[[0,0],[-9.354,1.436]],"o":[[3.892,-8.254],[0,0]],"v":[[-15.772,-3.905],[3.973,-19.095]],"c":false}]}],"ix":2},"nm":"Path 1","mn":"ADBE Vector Shape - Group","hd":false},{"ty":"st","c":{"a":0,"k":[0.317647058824,0.149019607843,0.094117654539,1],"ix":3},"o":{"a":0,"k":100,"ix":4},"w":{"a":0,"k":6,"ix":5},"lc":2,"lj":2,"bm":0,"nm":"Stroke 1","mn":"ADBE Vector Graphic - Stroke","hd":false},{"ty":"tr","p":{"a":0,"k":[31.069,42.251],"ix":2},"a":{"a":0,"k":[0,0],"ix":1},"s":{"a":0,"k":[100,100],"ix":3},"r":{"a":0,"k":0,"ix":6},"o":{"a":0,"k":100,"ix":7},"sk":{"a":0,"k":0,"ix":4},"sa":{"a":0,"k":0,"ix":5},"nm":"Transform"}],"nm":"Group 3","np":2,"cix":2,"bm":0,"ix":3,"mn":"ADBE Vector Group","hd":false},{"ty":"gr","it":[{"ind":0,"ty":"sh","ix":1,"ks":{"a":1,"k":[{"i":{"x":0.65,"y":1},"o":{"x":0.34,"y":0},"t":0,"s":[{"i":[[0,0],[-13.76,-0.874]],"o":[[2.283,-7.377],[0,0]],"v":[[-24.724,-5.731],[8.724,-23.269]],"c":false}]},{"i":{"x":0.65,"y":1},"o":{"x":0.34,"y":0},"t":20,"s":[{"i":[[0,0],[-7.26,-5.124]],"o":[[11.188,-1.412],[0,0]],"v":[[-29.974,-118.481],[-2.276,-112.019]],"c":false}]},{"i":{"x":0.65,"y":1},"o":{"x":0.34,"y":0},"t":40,"s":[{"i":[[0,0],[-13.76,-0.874]],"o":[[2.283,-7.377],[0,0]],"v":[[-24.724,-5.731],[8.724,-23.269]],"c":false}]},{"i":{"x":0.65,"y":1},"o":{"x":0.34,"y":0},"t":60,"s":[{"i":[[0,0],[-7.26,-5.124]],"o":[[11.188,-1.412],[0,0]],"v":[[-29.974,-118.481],[-2.276,-112.019]],"c":false}]},{"t":80,"s":[{"i":[[0,0],[-13.76,-0.874]],"o":[[2.283,-7.377],[0,0]],"v":[[-24.724,-5.731],[8.724,-23.269]],"c":false}]}],"ix":2},"nm":"Path 1","mn":"ADBE Vector Shape - Group","hd":false},{"ty":"st","c":{"a":0,"k":[0.317647058824,0.149019607843,0.094117654539,1],"ix":3},"o":{"a":0,"k":100,"ix":4},"w":{"a":0,"k":6,"ix":5},"lc":2,"lj":2,"bm":0,"nm":"Stroke 1","mn":"ADBE Vector Graphic - Stroke","hd":false},{"ty":"tr","p":{"a":0,"k":[22.224,33.234],"ix":2},"a":{"a":0,"k":[0,0],"ix":1},"s":{"a":0,"k":[100,100],"ix":3},"r":{"a":0,"k":0,"ix":6},"o":{"a":0,"k":100,"ix":7},"sk":{"a":0,"k":0,"ix":4},"sa":{"a":0,"k":0,"ix":5},"nm":"Transform"}],"nm":"Group 4","np":2,"cix":2,"bm":0,"ix":4,"mn":"ADBE Vector Group","hd":false}],"ip":0,"op":140,"st":0,"ct":1,"bm":0},{"ddd":0,"ind":8,"ty":4,"nm":"face border","sr":1,"ks":{"o":{"a":0,"k":100,"ix":11},"r":{"a":0,"k":0,"ix":10},"p":{"a":0,"k":[250,254.167,0],"ix":2,"l":2},"a":{"a":0,"k":[161.25,151.083,0],"ix":1,"l":2},"s":{"a":0,"k":[100,100,100],"ix":6,"l":2}},"ao":0,"shapes":[{"ty":"gr","it":[{"ind":0,"ty":"sh","ix":1,"ks":{"a":1,"k":[{"i":{"x":0.69,"y":1},"o":{"x":0.28,"y":0},"t":0,"s":[{"i":[[0,-105.801],[112.637,-1.886],[0,75.444],[-87.621,0]],"o":[[0,75.444],[-119.469,2],[0,-103.271],[87.622,0]],"v":[[151,13.75],[0.469,150.834],[-171,14.783],[-12.531,-150.584]],"c":true}]},{"i":{"x":0.833,"y":1},"o":{"x":0.28,"y":0},"t":20,"s":[{"i":[[0,-105.801],[112.637,-1.886],[0,75.444],[-87.621,0]],"o":[[0,75.444],[-119.469,2],[0,-103.271],[87.622,0]],"v":[[160,13.583],[0.469,150.834],[-159,14.648],[0.469,-146.584]],"c":true}]},{"i":{"x":0.69,"y":1},"o":{"x":0.28,"y":0},"t":40,"s":[{"i":[[0,-105.801],[112.637,-1.886],[0,75.444],[-87.621,0]],"o":[[0,75.444],[-119.469,2],[0,-103.271],[87.622,0]],"v":[[151,13.75],[0.469,150.834],[-171,14.783],[-12.531,-150.584]],"c":true}]},{"i":{"x":0.833,"y":1},"o":{"x":0.28,"y":0},"t":60,"s":[{"i":[[0,-105.801],[112.637,-1.886],[0,75.444],[-87.621,0]],"o":[[0,75.444],[-119.469,2],[0,-103.271],[87.622,0]],"v":[[160,13.583],[0.469,150.834],[-159,14.648],[0.469,-146.584]],"c":true}]},{"t":80,"s":[{"i":[[0,-105.801],[112.637,-1.886],[0,75.444],[-87.621,0]],"o":[[0,75.444],[-119.469,2],[0,-103.271],[87.622,0]],"v":[[151,13.75],[0.469,150.834],[-171,14.783],[-12.531,-150.584]],"c":true}]}],"ix":2},"nm":"Path 1","mn":"ADBE Vector Shape - Group","hd":false},{"ty":"st","c":{"a":0,"k":[0.317647058824,0.149019607843,0.094117654539,1],"ix":3},"o":{"a":0,"k":100,"ix":4},"w":{"a":0,"k":6,"ix":5},"lc":1,"lj":1,"ml":4,"bm":0,"nm":"Stroke 1","mn":"ADBE Vector Graphic - Stroke","hd":false},{"ty":"tr","p":{"a":0,"k":[161.25,151.083],"ix":2},"a":{"a":0,"k":[0,0],"ix":1},"s":{"a":0,"k":[100,100],"ix":3},"r":{"a":0,"k":0,"ix":6},"o":{"a":0,"k":100,"ix":7},"sk":{"a":0,"k":0,"ix":4},"sa":{"a":0,"k":0,"ix":5},"nm":"Transform"}],"nm":"Group 2","np":2,"cix":2,"bm":0,"ix":1,"mn":"ADBE Vector Group","hd":false}],"ip":0,"op":140,"st":0,"ct":1,"bm":0},{"ddd":0,"ind":9,"ty":4,"nm":"face shadow","sr":1,"ks":{"o":{"a":0,"k":50,"ix":11},"r":{"a":0,"k":0,"ix":10},"p":{"a":0,"k":[250,250,0],"ix":2,"l":2},"a":{"a":0,"k":[0,0,0],"ix":1,"l":2},"s":{"a":0,"k":[100,100,100],"ix":6,"l":2}},"ao":0,"hasMask":true,"masksProperties":[{"inv":false,"mode":"a","pt":{"a":1,"k":[{"i":{"x":0.69,"y":1},"o":{"x":0.28,"y":0},"t":0,"s":[{"i":[[0,-105.801],[112.637,-1.886],[0,75.444],[-87.621,0]],"o":[[0,75.444],[-119.469,2],[0,-103.271],[87.622,0]],"v":[[150.75,18.334],[0.219,155.417],[-171.25,19.366],[-12.781,-146]],"c":true}]},{"i":{"x":0.833,"y":1},"o":{"x":0.28,"y":0},"t":20,"s":[{"i":[[0,-105.801],[112.637,-1.886],[0,75.444],[-87.621,0]],"o":[[0,75.444],[-119.469,2],[0,-103.271],[87.622,0]],"v":[[160.25,18.167],[0.719,155.417],[-158.75,19.232],[0.719,-142]],"c":true}]},{"i":{"x":0.69,"y":1},"o":{"x":0.28,"y":0},"t":40,"s":[{"i":[[0,-105.801],[112.637,-1.886],[0,75.444],[-87.621,0]],"o":[[0,75.444],[-119.469,2],[0,-103.271],[87.622,0]],"v":[[151.25,18.334],[0.719,155.417],[-170.75,19.366],[-12.281,-146]],"c":true}]},{"i":{"x":0.833,"y":1},"o":{"x":0.28,"y":0},"t":60,"s":[{"i":[[0,-105.801],[112.637,-1.886],[0,75.444],[-87.621,0]],"o":[[0,75.444],[-119.469,2],[0,-103.271],[87.622,0]],"v":[[160.25,17.667],[0.719,154.917],[-158.75,18.732],[0.719,-142.5]],"c":true}]},{"t":80,"s":[{"i":[[0,-105.801],[112.637,-1.886],[0,75.444],[-87.621,0]],"o":[[0,75.444],[-119.469,2],[0,-103.271],[87.622,0]],"v":[[151.25,17.834],[0.719,154.917],[-170.75,18.866],[-12.281,-146.5]],"c":true}]}],"ix":1},"o":{"a":0,"k":100,"ix":3},"x":{"a":0,"k":0,"ix":4},"nm":"Mask 1"}],"shapes":[{"ty":"gr","it":[{"ind":0,"ty":"sh","ix":1,"ks":{"a":0,"k":{"i":[[0,0],[161,-27],[0,0],[-216,50]],"o":[[0,0],[-161,27],[0,0],[216,-50]],"v":[[151,-12],[47,120],[-198,30],[53,205]],"c":true},"ix":2},"nm":"Path 1","mn":"ADBE Vector Shape - Group","hd":false},{"ty":"fl","c":{"a":0,"k":[0.670588235294,0.486274539723,0.415686304429,1],"ix":4},"o":{"a":0,"k":100,"ix":5},"r":1,"bm":0,"nm":"Fill 1","mn":"ADBE Vector Graphic - Fill","hd":false},{"ty":"tr","p":{"a":0,"k":[0,0],"ix":2},"a":{"a":0,"k":[0,0],"ix":1},"s":{"a":0,"k":[100,100],"ix":3},"r":{"a":0,"k":0,"ix":6},"o":{"a":0,"k":100,"ix":7},"sk":{"a":0,"k":0,"ix":4},"sa":{"a":0,"k":0,"ix":5},"nm":"Transform"}],"nm":"Shape 1","np":3,"cix":2,"bm":0,"ix":1,"mn":"ADBE Vector Group","hd":false}],"ip":0,"op":140,"st":0,"ct":1,"bm":1},{"ddd":0,"ind":10,"ty":4,"nm":"face","sr":1,"ks":{"o":{"a":0,"k":100,"ix":11},"r":{"a":0,"k":0,"ix":10},"p":{"a":0,"k":[250,254.167,0],"ix":2,"l":2},"a":{"a":0,"k":[161.25,151.083,0],"ix":1,"l":2},"s":{"a":0,"k":[100,100,100],"ix":6,"l":2}},"ao":0,"shapes":[{"ty":"gr","it":[{"d":1,"ty":"el","s":{"a":0,"k":[238,153],"ix":2},"p":{"a":0,"k":[0,0],"ix":3},"nm":"Ellipse Path 1","mn":"ADBE Vector Shape - Ellipse","hd":false},{"ty":"fl","c":{"a":0,"k":[0.992156862745,0.937254901961,0.835294117647,1],"ix":4},"o":{"a":0,"k":100,"ix":5},"r":1,"bm":0,"nm":"Fill 1","mn":"ADBE Vector Graphic - Fill","hd":false},{"ty":"tr","p":{"a":1,"k":[{"i":{"x":0.75,"y":1},"o":{"x":0.24,"y":0},"t":0,"s":[183.25,220.417],"to":[0,0],"ti":[0,0]},{"i":{"x":0.75,"y":1},"o":{"x":0.24,"y":0},"t":20,"s":[121.25,220.917],"to":[0,0],"ti":[0,0]},{"i":{"x":0.75,"y":1},"o":{"x":0.24,"y":0},"t":40,"s":[183.25,220.417],"to":[0,0],"ti":[0,0]},{"i":{"x":0.75,"y":1},"o":{"x":0.24,"y":0},"t":60,"s":[121.25,220.917],"to":[0,0],"ti":[0,0]},{"t":80,"s":[183.25,220.417]}],"ix":2},"a":{"a":0,"k":[0,0],"ix":1},"s":{"a":1,"k":[{"i":{"x":[0.75,0.75],"y":[1,1]},"o":{"x":[0.24,0.24],"y":[0,0]},"t":0,"s":[104,100]},{"i":{"x":[0.75,0.75],"y":[1,1]},"o":{"x":[0.24,0.24],"y":[0,0]},"t":20,"s":[99.575,100]},{"i":{"x":[0.75,0.75],"y":[1,1]},"o":{"x":[0.24,0.24],"y":[0,0]},"t":40,"s":[104,100]},{"i":{"x":[0.75,0.75],"y":[1,1]},"o":{"x":[0.24,0.24],"y":[0,0]},"t":60,"s":[99.575,100]},{"t":80,"s":[104,100]}],"ix":3},"r":{"a":1,"k":[{"i":{"x":[0.75],"y":[1]},"o":{"x":[0.24],"y":[0]},"t":0,"s":[-13.996]},{"i":{"x":[0.75],"y":[1]},"o":{"x":[0.24],"y":[0]},"t":20,"s":[20.785]},{"i":{"x":[0.75],"y":[1]},"o":{"x":[0.24],"y":[0]},"t":40,"s":[-13.996]},{"i":{"x":[0.75],"y":[1]},"o":{"x":[0.24],"y":[0]},"t":60,"s":[20.785]},{"t":80,"s":[-13.996]}],"ix":6},"o":{"a":0,"k":100,"ix":7},"sk":{"a":0,"k":0,"ix":4},"sa":{"a":0,"k":0,"ix":5},"nm":"Transform"}],"nm":"Ellipse 1","np":2,"cix":2,"bm":0,"ix":1,"mn":"ADBE Vector Group","hd":false},{"ty":"gr","it":[{"ind":0,"ty":"sh","ix":1,"ks":{"a":1,"k":[{"i":{"x":0.69,"y":1},"o":{"x":0.28,"y":0},"t":0,"s":[{"i":[[0,-105.801],[112.637,-1.886],[0,75.444],[-87.621,0]],"o":[[0,75.444],[-119.469,2],[0,-103.271],[87.622,0]],"v":[[151,13.75],[0.469,150.834],[-171,14.783],[-12.531,-150.584]],"c":true}]},{"i":{"x":0.833,"y":1},"o":{"x":0.28,"y":0},"t":20,"s":[{"i":[[0,-105.801],[112.637,-1.886],[0,75.444],[-87.621,0]],"o":[[0,75.444],[-119.469,2],[0,-103.271],[87.622,0]],"v":[[160,13.583],[0.469,150.834],[-159,14.648],[0.469,-146.584]],"c":true}]},{"i":{"x":0.69,"y":1},"o":{"x":0.28,"y":0},"t":40,"s":[{"i":[[0,-105.801],[112.637,-1.886],[0,75.444],[-87.621,0]],"o":[[0,75.444],[-119.469,2],[0,-103.271],[87.622,0]],"v":[[151,13.75],[0.469,150.834],[-171,14.783],[-12.531,-150.584]],"c":true}]},{"i":{"x":0.833,"y":1},"o":{"x":0.28,"y":0},"t":60,"s":[{"i":[[0,-105.801],[112.637,-1.886],[0,75.444],[-87.621,0]],"o":[[0,75.444],[-119.469,2],[0,-103.271],[87.622,0]],"v":[[160,13.583],[0.469,150.834],[-159,14.648],[0.469,-146.584]],"c":true}]},{"t":80,"s":[{"i":[[0,-105.801],[112.637,-1.886],[0,75.444],[-87.621,0]],"o":[[0,75.444],[-119.469,2],[0,-103.271],[87.622,0]],"v":[[151,13.75],[0.469,150.834],[-171,14.783],[-12.531,-150.584]],"c":true}]}],"ix":2},"nm":"Path 1","mn":"ADBE Vector Shape - Group","hd":false},{"ty":"fl","c":{"a":0,"k":[0.670588235294,0.486274539723,0.415686304429,1],"ix":4},"o":{"a":0,"k":100,"ix":5},"r":1,"bm":0,"nm":"Fill 1","mn":"ADBE Vector Graphic - Fill","hd":false},{"ty":"tr","p":{"a":0,"k":[161.25,151.083],"ix":2},"a":{"a":0,"k":[0,0],"ix":1},"s":{"a":0,"k":[100,100],"ix":3},"r":{"a":0,"k":0,"ix":6},"o":{"a":0,"k":100,"ix":7},"sk":{"a":0,"k":0,"ix":4},"sa":{"a":0,"k":0,"ix":5},"nm":"Transform"}],"nm":"Group 2","np":2,"cix":2,"bm":0,"ix":2,"mn":"ADBE Vector Group","hd":false}],"ip":0,"op":140,"st":0,"ct":1,"bm":0},{"ddd":0,"ind":11,"ty":4,"nm":"ear","sr":1,"ks":{"o":{"a":0,"k":100,"ix":11},"r":{"a":0,"k":0,"ix":10},"p":{"a":0,"k":[250,162.972,0],"ix":2,"l":2},"a":{"a":0,"k":[181.44,68.638,0],"ix":1,"l":2},"s":{"a":0,"k":[100,100,100],"ix":6,"l":2}},"ao":0,"shapes":[{"ty":"gr","it":[{"ind":0,"ty":"sh","ix":1,"ks":{"a":1,"k":[{"i":{"x":0.7,"y":1},"o":{"x":0.34,"y":0},"t":0,"s":[{"i":[[0,0],[0,0],[5.421,-13.907]],"o":[[0,0],[0,0],[-5.394,13.837]],"v":[[-39.655,20.745],[-57.066,-16.47],[3.734,1.633]],"c":true}]},{"i":{"x":0.7,"y":1},"o":{"x":0.34,"y":0},"t":20,"s":[{"i":[[0,0],[0,0],[-7.361,-12.985]],"o":[[0,0],[0,0],[7.973,14.063]],"v":[[-11.155,49.245],[-40.566,-4.97],[39.734,-2.867]],"c":true}]},{"i":{"x":0.7,"y":1},"o":{"x":0.34,"y":0},"t":40,"s":[{"i":[[0,0],[0,0],[5.421,-13.907]],"o":[[0,0],[0,0],[-5.394,13.837]],"v":[[-39.655,20.745],[-57.066,-16.47],[3.734,1.633]],"c":true}]},{"i":{"x":0.7,"y":1},"o":{"x":0.34,"y":0},"t":60,"s":[{"i":[[0,0],[0,0],[-7.361,-12.985]],"o":[[0,0],[0,0],[7.973,14.063]],"v":[[-11.155,49.245],[-40.566,-4.97],[39.734,-2.867]],"c":true}]},{"t":80,"s":[{"i":[[0,0],[0,0],[5.421,-13.907]],"o":[[0,0],[0,0],[-5.394,13.837]],"v":[[-39.655,20.745],[-57.066,-16.47],[3.734,1.633]],"c":true}]}],"ix":2},"nm":"Path 1","mn":"ADBE Vector Shape - Group","hd":false},{"ty":"fl","c":{"a":0,"k":[0.964705942191,0.470588265213,0.709803921569,1],"ix":4},"o":{"a":0,"k":100,"ix":5},"r":1,"bm":0,"nm":"Fill 1","mn":"ADBE Vector Graphic - Fill","hd":false},{"ty":"tr","p":{"a":0,"k":[297.233,61.47],"ix":2},"a":{"a":0,"k":[0,0],"ix":1},"s":{"a":0,"k":[100,100],"ix":3},"r":{"a":0,"k":0,"ix":6},"o":{"a":0,"k":100,"ix":7},"sk":{"a":0,"k":0,"ix":4},"sa":{"a":0,"k":0,"ix":5},"nm":"Transform"}],"nm":"Group 1","np":2,"cix":2,"bm":0,"ix":1,"mn":"ADBE Vector Group","hd":false},{"ty":"gr","it":[{"ind":0,"ty":"sh","ix":1,"ks":{"a":1,"k":[{"i":{"x":0.7,"y":1},"o":{"x":0.34,"y":0},"t":0,"s":[{"i":[[0,0],[-26.236,26.488],[64,-5.333]],"o":[[34.542,-7.874],[-14.213,-27.899],[0,0]],"v":[[-25.624,53.305],[34.606,-3.74],[-95.607,-37.472]],"c":true}]},{"i":{"x":0.7,"y":1},"o":{"x":0.34,"y":0},"t":20,"s":[{"i":[[0,0],[-5.94,54.101],[49.273,-13.167]],"o":[[34.542,-7.874],[-30.94,-18.399],[0,0]],"v":[[-8.124,69.305],[77.106,-34.74],[-59.107,-36.972]],"c":true}]},{"i":{"x":0.7,"y":1},"o":{"x":0.34,"y":0},"t":40,"s":[{"i":[[0,0],[-26.236,26.488],[64,-5.333]],"o":[[34.542,-7.874],[-14.213,-27.899],[0,0]],"v":[[-25.624,53.305],[34.606,-3.74],[-95.607,-37.472]],"c":true}]},{"i":{"x":0.7,"y":1},"o":{"x":0.34,"y":0},"t":60,"s":[{"i":[[0,0],[-5.94,54.101],[49.273,-13.167]],"o":[[34.542,-7.874],[-30.94,-18.399],[0,0]],"v":[[-8.124,69.305],[77.106,-34.74],[-59.107,-36.972]],"c":true}]},{"t":80,"s":[{"i":[[0,0],[-26.236,26.488],[64,-5.333]],"o":[[34.542,-7.874],[-14.213,-27.899],[0,0]],"v":[[-25.624,53.305],[34.606,-3.74],[-95.607,-37.472]],"c":true}]}],"ix":2},"nm":"Path 1","mn":"ADBE Vector Shape - Group","hd":false},{"ty":"st","c":{"a":0,"k":[0.317647058824,0.149019607843,0.094117654539,1],"ix":3},"o":{"a":0,"k":100,"ix":4},"w":{"a":0,"k":6,"ix":5},"lc":2,"lj":2,"bm":0,"nm":"Stroke 1","mn":"ADBE Vector Graphic - Stroke","hd":false},{"ty":"fl","c":{"a":0,"k":[0.427451010311,0.160784313725,0.090196078431,1],"ix":4},"o":{"a":0,"k":100,"ix":5},"r":1,"bm":0,"nm":"Fill 1","mn":"ADBE Vector Graphic - Fill","hd":false},{"ty":"tr","p":{"a":0,"k":[282.773,68.305],"ix":2},"a":{"a":0,"k":[0,0],"ix":1},"s":{"a":0,"k":[100,100],"ix":3},"r":{"a":0,"k":0,"ix":6},"o":{"a":0,"k":100,"ix":7},"sk":{"a":0,"k":0,"ix":4},"sa":{"a":0,"k":0,"ix":5},"nm":"Transform"}],"nm":"Group 2","np":3,"cix":2,"bm":0,"ix":2,"mn":"ADBE Vector Group","hd":false},{"ty":"gr","it":[{"ind":0,"ty":"sh","ix":1,"ks":{"a":1,"k":[{"i":{"x":0.7,"y":1},"o":{"x":0.34,"y":0},"t":0,"s":[{"i":[[0,0],[0,0],[5.527,-16.104]],"o":[[0,0],[0,0],[-4.821,14.047]],"v":[[-8.344,39.245],[14.066,-12.97],[-50.234,-14.367]],"c":true}]},{"i":{"x":0.7,"y":1},"o":{"x":0.34,"y":0},"t":20,"s":[{"i":[[0,0],[0,0],[-0.973,-10.604]],"o":[[0,0],[0,0],[1.356,14.789]],"v":[[21.656,37.745],[37.566,-2.97],[-32.734,12.133]],"c":true}]},{"i":{"x":0.7,"y":1},"o":{"x":0.34,"y":0},"t":40,"s":[{"i":[[0,0],[0,0],[5.527,-16.104]],"o":[[0,0],[0,0],[-4.821,14.047]],"v":[[-8.344,39.245],[14.066,-12.97],[-50.234,-14.367]],"c":true}]},{"i":{"x":0.7,"y":1},"o":{"x":0.34,"y":0},"t":60,"s":[{"i":[[0,0],[0,0],[-0.973,-10.604]],"o":[[0,0],[0,0],[1.356,14.789]],"v":[[21.656,37.745],[37.566,-2.97],[-32.734,12.133]],"c":true}]},{"t":80,"s":[{"i":[[0,0],[0,0],[5.527,-16.104]],"o":[[0,0],[0,0],[-4.821,14.047]],"v":[[-8.344,39.245],[14.066,-12.97],[-50.234,-14.367]],"c":true}]}],"ix":2},"nm":"Path 1","mn":"ADBE Vector Shape - Group","hd":false},{"ty":"fl","c":{"a":0,"k":[0.964705942191,0.470588265213,0.709803921569,1],"ix":4},"o":{"a":0,"k":100,"ix":5},"r":1,"bm":0,"nm":"Fill 1","mn":"ADBE Vector Graphic - Fill","hd":false},{"ty":"tr","p":{"a":0,"k":[65.647,62.137],"ix":2},"a":{"a":0,"k":[0,0],"ix":1},"s":{"a":0,"k":[100,100],"ix":3},"r":{"a":0,"k":0,"ix":6},"o":{"a":0,"k":100,"ix":7},"sk":{"a":0,"k":0,"ix":4},"sa":{"a":0,"k":0,"ix":5},"nm":"Transform"}],"nm":"Group 3","np":2,"cix":2,"bm":0,"ix":3,"mn":"ADBE Vector Group","hd":false},{"ty":"gr","it":[{"ind":0,"ty":"sh","ix":1,"ks":{"a":1,"k":[{"i":{"x":0.7,"y":1},"o":{"x":0.34,"y":0},"t":0,"s":[{"i":[[0,0],[5.94,36.934],[-49.273,-7.333]],"o":[[-36.29,-16.11],[29.44,-15.566],[0,0]],"v":[[-19.377,59.805],[-85.607,-32.239],[33.107,-45.472]],"c":true}]},{"i":{"x":0.7,"y":1},"o":{"x":0.34,"y":0},"t":20,"s":[{"i":[[0,0],[26.236,26.487],[-64,-5.333]],"o":[[-34.541,-7.874],[9.44,-15.566],[0,0]],"v":[[25.624,53.305],[-65.107,5.761],[66.107,-36.972]],"c":true}]},{"i":{"x":0.7,"y":1},"o":{"x":0.34,"y":0},"t":40,"s":[{"i":[[0,0],[5.94,36.934],[-49.273,-7.333]],"o":[[-36.29,-16.11],[29.44,-15.566],[0,0]],"v":[[-19.377,59.805],[-85.607,-32.239],[33.107,-45.472]],"c":true}]},{"i":{"x":0.7,"y":1},"o":{"x":0.34,"y":0},"t":60,"s":[{"i":[[0,0],[26.236,26.487],[-64,-5.333]],"o":[[-34.541,-7.874],[9.44,-15.566],[0,0]],"v":[[25.624,53.305],[-65.107,5.761],[66.107,-36.972]],"c":true}]},{"t":80,"s":[{"i":[[0,0],[5.94,36.934],[-49.273,-7.333]],"o":[[-36.29,-16.11],[29.44,-15.566],[0,0]],"v":[[-19.377,59.805],[-85.607,-32.239],[33.107,-45.472]],"c":true}]}],"ix":2},"nm":"Path 1","mn":"ADBE Vector Shape - Group","hd":false},{"ty":"st","c":{"a":0,"k":[0.317647058824,0.149019607843,0.094117654539,1],"ix":3},"o":{"a":0,"k":100,"ix":4},"w":{"a":0,"k":6,"ix":5},"lc":2,"lj":2,"bm":0,"nm":"Stroke 1","mn":"ADBE Vector Graphic - Stroke","hd":false},{"ty":"fl","c":{"a":0,"k":[0.427451010311,0.160784313725,0.090196078431,1],"ix":4},"o":{"a":0,"k":100,"ix":5},"r":1,"bm":0,"nm":"Fill 1","mn":"ADBE Vector Graphic - Fill","hd":false},{"ty":"tr","p":{"a":0,"k":[80.107,68.972],"ix":2},"a":{"a":0,"k":[0,0],"ix":1},"s":{"a":0,"k":[100,100],"ix":3},"r":{"a":0,"k":0,"ix":6},"o":{"a":0,"k":100,"ix":7},"sk":{"a":0,"k":0,"ix":4},"sa":{"a":0,"k":0,"ix":5},"nm":"Transform"}],"nm":"Group 4","np":3,"cix":2,"bm":0,"ix":4,"mn":"ADBE Vector Group","hd":false}],"ip":0,"op":140,"st":0,"ct":1,"bm":0}]}],"layers":[{"ddd":0,"ind":1,"ty":0,"nm":"02. Animation","refId":"comp_0","sr":1,"ks":{"o":{"a":0,"k":100,"ix":11},"r":{"a":0,"k":0,"ix":10},"p":{"a":0,"k":[250,250,0],"ix":2,"l":2},"a":{"a":0,"k":[250,250,0],"ix":1,"l":2},"s":{"a":0,"k":[100,100,100],"ix":6,"l":2}},"ao":0,"w":500,"h":500,"ip":0,"op":140,"st":0,"bm":0}],"markers":[],"props":{}}